Metadata-Version: 2.1
Name: xllms
Version: 0.1.1
Summary: Easy '1-line' calling of all LLMs from OpenAI, MS Azure, AWS Bedrock, and GCP Vertex
Home-page: https://github.com/ventz/xllms
Author: Ventz Petkov
License: MIT
Classifier: Programming Language :: Python :: 3
Classifier: License :: OSI Approved :: MIT License
Classifier: Operating System :: OS Independent
Requires-Python: >=3.6
License-File: LICENSE
Requires-Dist: langchain ==0.1.20
Requires-Dist: langchain-community
Requires-Dist: langchain-openai
Requires-Dist: langchain-aws
Requires-Dist: langchain-google-vertexai ==1.0.3
Requires-Dist: python-dotenv
Requires-Dist: boto3
